{
  "path":{
    "source": "/home/caroline/Documents/parIdf/output/Output/csv",
    "destination": "/home/caroline/Documents/parIdf/output",
    "filename": "file"
  },
  "results": {
      "Temperatures.csv": {
        "meter": false,
        "columns": [
            "Environment:Site Outdoor Air Drybulb Temperature [C](Hourly)",
            "ZN1:Zone Mean Air Temperature [C](Hourly)",
            "ZN1:Zone Operative Temperature [C](Hourly)",
            "ZN1:Zone Mean Radiant Temperature [C](Hourly)"
        ]
      },
      "OpeningFactor.csv": {
        "meter": false,
        "columns": [
            "ZN1_PAR1_JAN:AFN Surface Venting Window or Door Opening Factor [](Hourly)",
            "ZN1_PAR4_JAN:AFN Surface Venting Window or Door Opening Factor [](Hourly)"
        ]
      },
      "NaturalVentilation.csv": {
        "meter": false,
        "columns": [
            "ZN1:AFN Zone Infiltration Volume [m3](Hourly)",
            "ZN1:AFN Zone Infiltration Air Change Rate [ach](Hourly)"
        ]
      },
      "HybridControl.csv": {
        "meter": false,
        "columns": [
            "ZN1:Availability Manager Hybrid Ventilation Control Status [](Hourly)",
            "ZN1:Availability Manager Hybrid Ventilation Control Mode [](Hourly)"
        ]
      },
      "IdealAirConditioning.csv": {
        "meter": false,
        "columns": [
            "ZN1 IDEAL LOADS AIR SYSTEM:Zone Ideal Loads Supply Air Sensible Cooling Energy [J](Hourly)",
            "ZN1 IDEAL LOADS AIR SYSTEM:Zone Ideal Loads Supply Air Total Cooling Energy [J](Hourly)"
        ]
      },
      "TotalPowerConsumption.csv": {
        "meter": false,
        "columns": [
            "Electricity:Facility [J](Hourly)",
            "DistrictCooling:Facility [J](Hourly)"
        ]
      },
      "CO2eCarbonEquivalent.csv": {
        "meter": false,
        "columns": [
            "CO2:Facility [kg](Hourly)",
            "Carbon Equivalent:Facility [kg](Hourly) "
        ]
      }
  }
}
